README.md
setup.py
test/test_auth.py
test/test_ccxt.py
test/test_charting.py
test/test_poll.py
test/test_settings.py
uxs/__init__.py
uxs/binance.py
uxs/binancefu.py
uxs/bitmex.py
uxs/bittrex.py
uxs/bw.py
uxs/coinbene.py
uxs/coinbeneswap.py
uxs/coindcx.py
uxs/gateiofu.py
uxs/hitbtc.py
uxs/kraken.py
uxs/krakenfu.py
uxs/kucoin.py
uxs/luno.py
uxs/poloniex.py
uxs/southxchange.py
uxs/test_xc.py
uxs.egg-info/PKG-INFO
uxs.egg-info/SOURCES.txt
uxs.egg-info/dependency_links.txt
uxs.egg-info/requires.txt
uxs.egg-info/top_level.txt
uxs/_data/luno_markets.json
uxs/_data/poloniex_currency_ids.txt
uxs/_data/poloniex_currency_pair_ids.txt
uxs/_data/southxchange_markets.json
uxs/base/__init__.py
uxs/base/_settings.py
uxs/base/auth.py
uxs/base/ccxt.py
uxs/base/poll.py
uxs/base/socket/__init__.py
uxs/base/socket/errors.py
uxs/base/socket/exchange.py
uxs/base/socket/l3.py
uxs/base/socket/orderbook.py
uxs/base/wrappers/__init__.py
uxs/base/wrappers/binancefu.py
uxs/base/wrappers/bitmex.py
uxs/base/wrappers/bittrex.py
uxs/base/wrappers/btsefu.py
uxs/base/wrappers/bw.py
uxs/base/wrappers/coinbene.py
uxs/base/wrappers/dragonex.py
uxs/base/wrappers/hitbtc.py
uxs/base/wrappers/krakenfu.py
uxs/base/wrappers/luno.py
uxs/base/wrappers/poloniex.py
uxs/base/wrappers/southxchange.py
uxs/base/wrappers/async_support/__init__.py
uxs/base/wrappers/async_support/luno.py
uxs/base/wrappers/async_support/southxchange.py
uxs/base/wrappers/sync_support/__init__.py
uxs/base/wrappers/sync_support/luno.py
uxs/base/wrappers/sync_support/southxchange.py
uxs/fintls/__init__.py
uxs/fintls/basics.py
uxs/fintls/charting.py
uxs/fintls/l3.py
uxs/fintls/margin.py
uxs/fintls/misc.py
uxs/fintls/ob.py
uxs/fintls/ohlcv.py
uxs/fintls/shapes.py
uxs/fintls/utils.py
uxs/ui/__init__.py
uxs/ui/_queue.py
uxs/ui/desk.py
uxs/ui/stoploss.py