Metadata-Version: 2.1
Name: uxs
Version: 0.6.0
Summary: A unified crypto exchange websocket
Home-page: https://github.com/binares/uxs
Author: binares
Author-email: binares@protonmail.com
License: UNKNOWN
Platform: UNKNOWN
Requires-Python: >=3.5.3
